{
  "appFunctions": {
    "myFunc": {
      "file": "example-function.js",
      "secrets": []
    },
    "addLineItem": {
      "file": "add-line-item-function.js",
      "secrets": []
    },
    "newAddLineItem": {
      "file": "new-add-line-item-function.js",
      "secrets": []
    },
    "getLineItems": {
      "file": "get-deal-line-items-function.js",
      "secrets": []
    },
    "deleteLineItems": {
      "file": "delete-line-items-function.js",
      "secrets": []
    },
    "MeetingLog": {
      "file": "meeting-log-function.js",
      "secrets": []
    }
  }
}